dfe_nfse-0.1.3.dist-info/licenses/LICENSE
nfse/__init__.py
dfe_nfse-0.1.3.dist-info/METADATA
dfe_nfse-0.1.3.dist-info/WHEEL
dfe_nfse-0.1.3.dist-info/top_level.txt
dfe_nfse-0.1.3.dist-info/RECORD
