Metadata-Version: 2.4
Name: dfe-nfse
Version: 0.1.3
Summary: Biblioteca para baixar NFSe do Ambiente Nacional (ADN)
Home-page: https://github.com/DaavidSiilva/dfe-nfse
Author: David Silva
Author-email: david.emery.silva@gmail.com
Project-URL: Homepage, https://tax-transformation.com/
Project-URL: Repository, https://github.com/DaavidSiilva/dfe-nfse
Project-URL: linkedin, https://www.linkedin.com/in/davidm-silva/
Classifier: Programming Language :: Python :: 3
Classifier: License :: OSI Approved :: MIT License
Classifier: Operating System :: OS Independent
Requires-Python: >=3.6
License-File: LICENSE
Requires-Dist: requests
Requires-Dist: cryptography
Dynamic: author
Dynamic: author-email
Dynamic: classifier
Dynamic: description
Dynamic: description-content-type
Dynamic: home-page
Dynamic: license-file
Dynamic: project-url
Dynamic: requires-dist
Dynamic: requires-python
Dynamic: summary
